<Properties StartupConfiguration="{83AEFCAE-5C27-4C2F-B368-F8D04E0E0F31}|Default">
  <MonoDevelop.Ide.Workspace ActiveConfiguration="Debug" />
  <MonoDevelop.Ide.ItemProperties.L8__MAMP__1155326 PreferredExecutionTarget="MonoDevelop.Default" />
  <MonoDevelop.Ide.Workbench ActiveDocument="L8_MAMP_1155326/Program.cs">
    <Files>
      <File FileName="L8_MAMP_1155326/Program.cs" Line="163" Column="2" />
    </Files>
  </MonoDevelop.Ide.Workbench>
  <MultiItemStartupConfigurations />
  <MonoDevelop.Ide.DebuggingService.PinnedWatches />
  <MonoDevelop.Ide.DebuggingService.Breakpoints>
    <BreakpointStore />
  </MonoDevelop.Ide.DebuggingService.Breakpoints>
</Properties>